altair_images/__init__.py
altair_images/proxy.py
altair_images/serving.py
altair_images/thread.py
altair_images-0.1.4.dist-info/LICENSE
altair_images-0.1.4.dist-info/METADATA
altair_images-0.1.4.dist-info/WHEEL
altair_images-0.1.4.dist-info/top_level.txt
altair_images-0.1.4.dist-info/RECORD
