Metadata-Version: 2.1
Name: altair-images
Version: 0.1.4
Summary: Serving interactive charts with images
Home-page: https://github.com/lc0/altair_images
Author: Sergii Khomenko
License: UNKNOWN
Keywords: altair flask colab ngrok demo
Platform: UNKNOWN
Classifier: Development Status :: 4 - Beta 
Classifier: Programming Language :: Python :: 3.7
Classifier: Intended Audience :: Developers
Classifier: Intended Audience :: Education
Classifier: License :: OSI Approved :: MIT License
Classifier: Operating System :: OS Independent
Requires-Dist: Flask (==1.0.2)
Requires-Dist: Flask-Cors (==3.0.8)
Requires-Dist: Pillow (==7.1.1)
Requires-Dist: pyngrok (==2.1.3)
